{
	"$schema": "https://biomejs.dev/schemas/2.4.10/schema.json",
	"vcs": {
		"enabled": true,
		"clientKind": "git",
		"useIgnoreFile": true
	},
	"files": {
		"includes": [
			"apps/**/*.ts",
			"apps/**/*.tsx",
			"packages/**/*.ts",
			"packages/**/*.tsx",
			"*.config.ts",
			"*.config.mjs",
			"!**/.next",
			"!**/dist"
		]
	},
	"formatter": {
		"enabled": true,
		"indentStyle": "tab",
		"lineWidth": 100
	},
	"linter": {
		"enabled": true,
		"rules": {
			"recommended": true
		}
	},
	"overrides": [
		{
			"includes": ["apps/nest-api/**/*.ts"],
			"javascript": {
				"parser": {
					"unsafeParameterDecoratorsEnabled": true
				},
				"formatter": {
					"quoteStyle": "single",
					"trailingCommas": "all"
				}
			},
			"linter": {
				"rules": {
					"style": {
						"useImportType": "off"
					},
					"suspicious": {
						"noExplicitAny": "off"
					},
					"nursery": {
						"noFloatingPromises": "warn"
					}
				}
			}
		},
		{
			"includes": ["apps/mobile/**/*.ts", "apps/mobile/**/*.tsx"],
			"linter": {
				"rules": {
					"suspicious": {
						"noArrayIndexKey": "off"
					}
				}
			}
		}
	]
}
